pyactms/__init__.py
pyactms/actms.py
pyactms/actr.py
pyactms-0.0.2.dist-info/LICENSE.md
pyactms-0.0.2.dist-info/METADATA
pyactms-0.0.2.dist-info/WHEEL
pyactms-0.0.2.dist-info/top_level.txt
pyactms-0.0.2.dist-info/RECORD
